{
  "team_key": "388.l.111208.t.2",
  "team_id": "2",
  "name": "Beer Batters",
  "is_owned_by_current_login": 1,
  "url": "https://baseball.fantasysports.yahoo.com/2019/b1/111208/2",
  "team_logos": [
    {
      "size": "large",
      "url": "https://yahoofantasysports-res.cloudinary.com/image/upload/t_s192sq/fantasy-logos/58845401912_fb2570.jpg"
    }
  ],
  "waiver_priority": 4,
  "number_of_moves": "12",
  "number_of_trades": "2",
  "roster_adds": {
    "coverage_type": "week",
    "coverage_value": "25",
    "value": "0"
  },
  "league_scoring_type": "head",
  "has_draft_grade": 0,
  "managers": [
    {
      "manager_id": "2",
      "nickname": "Charles Haviland",
      "guid": "4EJ3QGL6K4NIP6SQQSV4PIRMG4",
      "is_current_login": "1",
      "image_url": "https://s.yimg.com/ag/images/default_user_profile_pic_64sq.jpg",
      "felo_score": "548",
      "felo_tier": "bronze"
    }
  ],
  "stats": [
    {
      "stat_id": "60",
      "value": "83/297",
      "display_name": "H/AB"
    },
    {
      "stat_id": "7",
      "value": "47",
      "display_name": "R"
    },
    {
      "stat_id": "12",
      "value": "16",
      "display_name": "HR"
    },
    {
      "stat_id": "13",
      "value": "48",
      "display_name": "RBI"
    },
    {
      "stat_id": "16",
      "value": "11",
      "display_name": "SB"
    },
    {
      "stat_id": "4",
      "value": ".336",
      "display_name": "OBP"
    },
    {
      "stat_id": "61",
      "value": "30",
      "display_name": "XBH"
    },
    {
      "stat_id": "50",
      "value": "46.2",
      "display_name": "IP"
    },
    {
      "stat_id": "42",
      "value": "49",
      "display_name": "K"
    },
    {
      "stat_id": "26",
      "value": "3.09",
      "display_name": "ERA"
    },
    {
      "stat_id": "27",
      "value": "1.01",
      "display_name": "WHIP"
    },
    {
      "stat_id": "57",
      "value": "9.45",
      "display_name": "K/9"
    },
    {
      "stat_id": "83",
      "value": "4",
      "display_name": "QS"
    },
    {
      "stat_id": "89",
      "value": "2",
      "display_name": "SV+H"
    }
  ]
}